ie_mbdbl2017_D_yahoo_ks_datareader
