Metadata-Version: 1.0
Name: ie-mbdbl2017-D-yahoo-ks-datareader
Version: 0.2
Summary: Python Packaging Starting Kit - Simple Structure to creater your own package - for training purposes!
Home-page: https://github.com/manoelgadi/ie_mbdbl2017_D_yahoo_ks_datareader
Author: Derrick Lichti
Author-email: dlichti@student.ie.edu
License: MIT
Platform: UNKNOWN
